dotify/__init__.py
dotify/__main__.py
dotify/cli.py
dotify/constants.py
dotify/custom_logger_formatter.py
dotify/downloader.py
dotify/downloader_audio.py
dotify/downloader_episode.py
dotify/downloader_episode_video.py
dotify/downloader_music_video.py
dotify/downloader_song.py
dotify/downloader_video.py
dotify/enums.py
dotify/models.py
dotify/spotify_api.py
dotify/totp.py
dotify/utils.py
dotify_cli-1.5.4.dist-info/entry_points.txt
dotify_cli-1.5.4.dist-info/licenses/LICENSE
dotify_cli-1.5.4.dist-info/WHEEL
dotify_cli-1.5.4.dist-info/METADATA
dotify_cli-1.5.4.dist-info/RECORD
