Metadata-Version: 2.4
Name: dotify-cli
Version: 1.5.4
Summary: A command-line app for downloading songs, podcasts and videos from Spotify.
Author: AsHfIEXE
Requires-Python: >=3.10
License-File: LICENSE
Requires-Dist: click
Requires-Dist: colorama
Requires-Dist: inquirerpy
Requires-Dist: mutagen
Requires-Dist: pillow
Requires-Dist: protobuf
Requires-Dist: pybase62
Requires-Dist: pycryptodome
Requires-Dist: pywidevine
Requires-Dist: yt-dlp
Requires-Dist: requests
Project-URL: Homepage, https://github.com/AsHfIEXE/Dotify
Project-URL: Repository, https://github.com/AsHfIEXE/Dotify
